setup.cfg
setup.py
Flask_Goat.egg-info/PKG-INFO
Flask_Goat.egg-info/SOURCES.txt
Flask_Goat.egg-info/dependency_links.txt
Flask_Goat.egg-info/not-zip-safe
Flask_Goat.egg-info/requires.txt
Flask_Goat.egg-info/top_level.txt
flask_goat/__init__.py