Metadata-Version: 1.1
Name: Flask-Goat
Version: 0.2.1
Summary: Flask plugin for security and user administration via GitHub OAuth & organization
Home-page: http://incontextsolutions.github.io/flask-goat/
Author: Tristan Wietsma
Author-email: tristan.wietsma@incontextsolutions.com
License: MIT
Platform: any
Classifier: Environment :: Web Environment
Classifier: Intended Audience :: Developers
Classifier: License :: OSI Approved :: MIT License
Classifier: Operating System :: OS Independent
Classifier: Programming Language :: Python
Classifier: Topic :: Internet :: WWW/HTTP :: Dynamic Content
Classifier: Topic :: Software Development :: Libraries :: Python Modules
